{
  "codes": {
    "97CWJOD1": {
      "roleId": "1411296365987889272",
      "duration": 30,
      "created": 1757424242445,
      "used": false,
      "usedBy": null,
      "usedAt": null
    },
    "KP7SWC3C": {
      "roleId": "1411296365987889272",
      "duration": 7,
      "created": 1758295216351,
      "used": false,
      "usedBy": null,
      "usedAt": null
    }
  },
  "userRoles": {
    "737155997440802926": {
      "1406957343815766149": {
        "roleId": "1411296365987889272",
        "expiryDate": 1760020041812,
        "code": "15TQS4NI",
        "duration": 30,
        "createdAt": 1757427859735,
        "redeemedAt": 1757428041812
      }
    },
    "1112377022602301510": {
      "1406957343815766149": {
        "roleId": "1412336702915219496",
        "expiryDate": 1760095108884,
        "code": "2GE6L098",
        "duration": 30,
        "createdAt": 1757497262057,
        "redeemedAt": 1757503108884
      }
    },
    "1274489297268904019": {
      "1406957343815766149": {
        "roleId": "1412336702915219496",
        "expiryDate": 1760356123171,
        "code": "MBB6UGMF",
        "duration": 30,
        "createdAt": 1757763656639,
        "redeemedAt": 1757764123171
      }
    },
    "296971813496291331": {
      "1406957343815766149": {
        "roleId": "1412336702915219496",
        "expiryDate": 1760898864770,
        "code": "ZZGAUPF4",
        "duration": 30,
        "createdAt": 1758306810844,
        "redeemedAt": 1758306864770
      }
    },
    "1242819681870544899": {
      "1406957343815766149": {
        "roleId": "1411296365987889272",
        "expiryDate": 1760963302651,
        "code": "G0AMNZTD",
        "duration": 30,
        "createdAt": 1758371214811,
        "redeemedAt": 1758371302651
      }
    },
    "747094380640206869": {
      "1406957343815766149": {
        "roleId": "1412336702915219496",
        "expiryDate": 1761120662803,
        "code": "CHSH14EK",
        "duration": 30,
        "createdAt": 1758528539294,
        "redeemedAt": 1758528662803
      }
    },
    "834666006261399562": {
      "1406957343815766149": {
        "roleId": "1412336702915219496",
        "expiryDate": 1761305736207,
        "code": "338ZQJXB",
        "duration": 30,
        "createdAt": 1758712949394,
        "redeemedAt": 1758713736207
      }
    },
    "823843270689030154": {
      "1406957343815766149": {
        "roleId": "1412336702915219496",
        "expiryDate": 1759913980536,
        "code": "UL6EUEHM",
        "duration": 7,
        "createdAt": 1759309100518,
        "redeemedAt": 1759309180536
      }
    },
    "1134531569508425768": {
      "1406957343815766149": {
        "roleId": "1412336702915219496",
        "expiryDate": 1759917938881,
        "code": "08BNLO9P",
        "duration": 7,
        "createdAt": 1759313064130,
        "redeemedAt": 1759313138881
      }
    },
    "473021283031056384": {
      "1406957343815766149": {
        "roleId": "1412336702915219496",
        "expiryDate": 1759926132424,
        "code": "8SF9P9B0",
        "duration": 7,
        "createdAt": 1759321229713,
        "redeemedAt": 1759321332424
      }
    },
    "1124686571103334491": {
      "1406957343815766149": {
        "roleId": "1411296365987889272",
        "expiryDate": 1759974337313,
        "code": "5U5PVESC",
        "duration": 7,
        "createdAt": 1759368751556,
        "redeemedAt": 1759369537313
      }
    },
    "997146552885854259": {
      "1406957343815766149": {
        "roleId": "1411296365987889272",
        "expiryDate": 1759988982959,
        "code": "3U924RAX",
        "duration": 7,
        "createdAt": 1759381137111,
        "redeemedAt": 1759384182959
      }
    },
    "569498794400415763": {
      "1406957343815766149": {
        "roleId": "1411296365987889272",
        "expiryDate": 1760091279918,
        "code": "5WA937JQ",
        "duration": 7,
        "createdAt": 1759485817169,
        "redeemedAt": 1759486479918
      }
    },
    "530727759887073280": {
      "1406957343815766149": {
        "roleId": "1412336702915219496",
        "expiryDate": 1762101620990,
        "code": "YGZ3M4JT",
        "duration": 30,
        "createdAt": 1759505973391,
        "redeemedAt": 1759509620990
      }
    },
    "461171424523190284": {
      "1406957343815766149": {
        "roleId": "1412336702915219496",
        "expiryDate": 1760284671248,
        "code": "8EIEKY4E",
        "duration": 7,
        "createdAt": 1759678918945,
        "redeemedAt": 1759679871248
      }
    },
    "1102958035967692943": {
      "1406957343815766149": {
        "roleId": "1411296365987889272",
        "expiryDate": 1762273289679,
        "code": "9RS4AKMA",
        "duration": 30,
        "createdAt": 1759678836515,
        "redeemedAt": 1759681289679
      }
    },
    "922039977217490954": {
      "1406957343815766149": {
        "roleId": "1411296365987889272",
        "expiryDate": 1759960050987,
        "code": "XE6HYCI8",
        "duration": 3,
        "createdAt": 1759678901304,
        "redeemedAt": 1759700850987
      }
    },
    "1123910114651406336": {
      "1406957343815766149": {
        "roleId": "1412336702915219496",
        "expiryDate": 1760376581312,
        "code": "TEYKZ41Q",
        "duration": 7,
        "createdAt": 1759771378672,
        "redeemedAt": 1759771781312
      }
    },
    "331679177306537994": {
      "1406957343815766149": {
        "roleId": "1412336702915219496",
        "expiryDate": 1760444690510,
        "code": "7FU6Y3WP",
        "duration": 7,
        "createdAt": 1759835840682,
        "redeemedAt": 1759839890510
      }
    },
    "1013317748643864706": {
      "1406957343815766149": {
        "roleId": "1411296365987889272",
        "expiryDate": 1762447316535,
        "code": "J3RL8E2S",
        "duration": 30,
        "createdAt": 1759855190921,
        "redeemedAt": 1759855316535
      }
    }
  }
}